Metadata-Version: 1.2
Name: eida-statistics-manager
Version: 0.2.0
Summary: EIDA nodes statistics manager
Home-page: https://github.com/eida/eida-statistics/manager
Author: Jonathan Schaeffer
Author-email: jonathan.schaeffer@univ-grenoble-alpes.fr
Maintainer: Jonathan Schaeffer
Maintainer-email: jonathan.schaeffer@univ-grenoble-alpes.fr
License: GPLv3
Platform: UNKNOWN
Classifier: Development Status :: 4 - Beta
Classifier: Intended Audience :: Developers
Classifier: License :: OSI Approved :: GNU General Public License v3 (GPLv3)
Classifier: Natural Language :: English
Classifier: Operating System :: OS Independent
Classifier: Programming Language :: Python :: 3
Requires-Python: >=3.6
